README.md
setup.py
src/gc/__init__.py
src/log/__init__.py
src/machine/__init__.py
src/microbit/__init__.py
src/microbit/accelerometer.py
src/microbit/audio.py
src/microbit/compass.py
src/microbit/display.py
src/microbit/i2c.py
src/microbit/microphone.py
src/microbit/speaker.py
src/microbit/spi.py
src/microbit/uart.py
src/microbit_stubs.egg-info/PKG-INFO
src/microbit_stubs.egg-info/SOURCES.txt
src/microbit_stubs.egg-info/dependency_links.txt
src/microbit_stubs.egg-info/top_level.txt
src/micropython/__init__.py
src/music/__init__.py
src/neopixel/__init__.py
src/power/__init__.py
src/radio/__init__.py
src/speech/__init__.py
src/struct/__init__.py
tests/test_stubs.py