Metadata-Version: 2.1
Name: microbit-stubs
Version: 0.1.0
Summary: Python stubs for micro:bit modules
Home-page: https://github.com/e-enes/microbit-stubs
Author: Enes Tahiri
Author-email: contact@enes.gg
License: MIT
Classifier: Development Status :: 3 - Alpha
Classifier: Intended Audience :: Developers
Classifier: License :: OSI Approved :: MIT License
Classifier: Programming Language :: Python
